corpus_base/__init__.py
corpus_base/__main__.py
corpus_base/decision.py
corpus_base/justice.py
corpus_base/segment.py
corpus_base/templates/chief_dates.sql
corpus_base/templates/get_justice_id.sql
corpus_base/templates/ids_to_investigate.sql
corpus_base/templates/update_justice_ids.sql
corpus_base/utils/__init__.py
corpus_base/utils/convertor.py
corpus_base/utils/ponente.py
corpus_base/utils/resources.py
corpus_base/utils/tags.py
corpus_base/utils/voteline.py
corpus_base-0.1.10.dist-info/WHEEL
corpus_base-0.1.10.dist-info/METADATA
corpus_base-0.1.10.dist-info/RECORD
